AUTHORS
CHANGES.rst
LICENSE
MANIFEST.in
README.rst
setup.py
test/test_opera1.py
test/test_opregister.py
test_steps/__init__.py
test_steps/ymal_testbed.py
test_steps.egg-info/PKG-INFO
test_steps.egg-info/SOURCES.txt
test_steps.egg-info/dependency_links.txt
test_steps.egg-info/top_level.txt