Metadata-Version: 1.1
Name: test-steps
Version: 0.8.8
Summary: Simple way to run test steps and automatic logging
Home-page: https://github.com/steven004/TestSteps
Author: Steven LI
Author-email: steven004@gmail.com
License: UNKNOWN
Platform: UNKNOWN
Classifier: Development Status :: 4 - Beta
Classifier: Intended Audience :: Developers
Classifier: License :: OSI Approved :: MIT License
Classifier: Operating System :: Unix
Classifier: Operating System :: Microsoft :: Windows
Classifier: Operating System :: MacOS :: MacOS X
Classifier: Topic :: Software Development :: Testing
Classifier: Topic :: Software Development :: Quality Assurance
Classifier: Topic :: Software Development :: Libraries
Classifier: Topic :: Utilities
Classifier: Topic :: System :: Logging
Classifier: Programming Language :: Python :: 3
